trelasticext/__init__.py
trelasticext/elastic_extension.py
trelasticext/heb_tokenizer.py
trelasticext-0.2.1.dist-info/licenses/LICENSE
trelasticext-0.2.1.dist-info/METADATA
trelasticext-0.2.1.dist-info/WHEEL
trelasticext-0.2.1.dist-info/top_level.txt
trelasticext-0.2.1.dist-info/RECORD
