Metadata-Version: 2.4
Name: trelasticext
Version: 0.2.1
Summary: Elasticsearch Extensions for Hebrew and Multi-language Text Processing
Home-page: https://github.com/millerhadar/trelasticext
Author: Hadar Miller
Author-email: Hadar Miller <hadar.miller@example.com>
License: MIT
Project-URL: Homepage, https://github.com/millerhadar/trelasticext
Project-URL: Documentation, https://github.com/millerhadar/trelasticext#readme
Project-URL: Repository, https://github.com/millerhadar/trelasticext
Project-URL: Bug Tracker, https://github.com/millerhadar/trelasticext/issues
Keywords: elasticsearch,hebrew,tokenizer,nlp,text-processing,linguistics
Classifier: Development Status :: 4 - Beta
Classifier: Intended Audience :: Science/Research
Classifier: Intended Audience :: Developers
Classifier: License :: OSI Approved :: MIT License
Classifier: Programming Language :: Python :: 3
Classifier: Programming Language :: Python :: 3.8
Classifier: Programming Language :: Python :: 3.9
Classifier: Programming Language :: Python :: 3.10
Classifier: Programming Language :: Python :: 3.11
Requires-Python: >=3.8
License-File: LICENSE
Requires-Dist: elasticsearch<9.0.0,>=7.0.0
Requires-Dist: pandas>=1.3.0
Requires-Dist: numpy>=1.20.0
Provides-Extra: dev
Requires-Dist: pytest>=6.0; extra == "dev"
Requires-Dist: pytest-cov>=2.0; extra == "dev"
Requires-Dist: black>=21.0; extra == "dev"
Requires-Dist: flake8>=3.9; extra == "dev"
Dynamic: author
Dynamic: home-page
Dynamic: license-file
Dynamic: requires-python
